{"title": "Bg. 11.24", "sanskrit": "\u0928\u092d:\u0938\u094d\u092a\u0943\u0936\u0902 \u0926\u0940\u092a\u094d\u200d\u0924\u092e\u0928\u0947\u0915\u0935\u0930\u094d\u0923\u0902\u0935\u094d\u092f\u093e\u0924\u094d\u0924\u093e\u0928\u0928\u0902 \u0926\u0940\u092a\u094d\u200d\u0924\u0935\u093f\u0936\u093e\u0932\u0928\u0947\u0924\u094d\u0930\u092e\u094d \u0964\u0926\u0943\u0937\u094d\u091f\u094d\u0935\u093e \u0939\u093f \u0924\u094d\u0935\u093e\u0902 \u092a\u094d\u0930\u0935\u094d\u092f\u0925\u093f\u0924\u093e\u0928\u094d\u0924\u0930\u093e\u0924\u094d\u092e\u093e\u0927\u0943\u0924\u093f\u0902 \u0928 \u0935\u093f\u0928\u094d\u0926\u093e\u092e\u093f \u0936\u092e\u0902 \u091a \u0935\u093f\u0937\u094d\u0923\u094b \u0965 \u0968\u096a \u0965", "transliteration": "nabha\u1e25-sp\u1e5b\u015ba\u1e41 d\u012bptam aneka-var\u1e47a\u1e41vy\u0101tt\u0101nana\u1e41 d\u012bpta-vi\u015b\u0101la-netramd\u1e5b\u1e63\u1e6dv\u0101 hi tv\u0101\u1e41 pravyathit\u0101ntar-\u0101tm\u0101dh\u1e5bti\u1e41 na vind\u0101mi \u015bama\u1e41 ca vi\u1e63\u1e47o", "words_trans": {"nabha\u1e25-sp\u1e5b\u015bam": "touching the sky", "d\u012bptam": "glowing", "aneka": "many", "var\u1e47am": "colors", "vy\u0101tta": "open", "\u0101nanam": "mouths", "d\u012bpta": "glowing", "vi\u015b\u0101la": "very great", "netram": "eyes", "d\u1e5b\u1e63\u1e6dv\u0101": "seeing", "hi": "certainly", "tv\u0101m": "You", "pravyathita": "perturbed", "anta\u1e25": "within", "\u0101tm\u0101": "soul", "dh\u1e5btim": "steadiness", "na": "not", "vind\u0101mi": "I have", "\u015bamam": "mental tranquillity", "ca": "also", "vi\u1e63\u1e47o": "O Lord Vi\u1e63\u1e47u."}, "literary_trans": "O all-pervading Vi\u1e63\u1e47u, seeing You with Your many radiant colors touching the sky, Your gaping mouths, and Your great glowing eyes, my mind is perturbed by fear. I can no longer maintain my steadiness or equilibrium of mind.O all-pervading Vi\u1e63\u1e47u, seeing You with Your many radiant colors touching the sky, Your gaping mouths, and Your great glowing eyes, my mind is perturbed by fear. I can no longer maintain my steadiness or equilibrium of mind."}