{"title": "Bg. 11.19", "sanskrit": "\u0905\u0928\u093e\u0926\u093f\u092e\u0927\u094d\u092f\u093e\u0928\u094d\u0924\u092e\u0928\u0928\u094d\u0924\u0935\u0940\u0930\u094d\u092f-\u092e\u0928\u0928\u094d\u0924\u092c\u093e\u0939\u0941\u0902 \u0936\u0936\u093f\u0938\u0942\u0930\u094d\u092f\u0928\u0947\u0924\u094d\u0930\u092e\u094d \u0964\u092a\u0936\u094d\u092f\u093e\u092e\u093f \u0924\u094d\u0935\u093e\u0902 \u0926\u0940\u092a\u094d\u200d\u0924\u0939\u0941\u0924\u093e\u0936\u0935\u0915\u094d\u200d\u0924\u094d\u0930\u0902\u0938\u094d\u0935\u0924\u0947\u091c\u0938\u093e \u0935\u093f\u0936\u094d\u0935\u092e\u093f\u0926\u0902 \u0924\u092a\u0928\u094d\u0924\u092e\u094d \u0965 \u0967\u096f \u0965", "transliteration": "an\u0101di-madhy\u0101ntam ananta-v\u012bryamananta-b\u0101hu\u1e41 \u015ba\u015bi-s\u016brya-netrampa\u015by\u0101mi tv\u0101\u1e41 d\u012bpta-hut\u0101\u015ba-vaktra\u1e41sva-tejas\u0101 vi\u015bvam ida\u1e41 tapantam", "words_trans": {"an\u0101di": "without beginning", "madhya": "middle", "antam": "or end", "ananta": "unlimited", "v\u012bryam": "glories", "b\u0101hum": "arms", "\u015ba\u015bi": "the moon", "s\u016brya": "and sun", "netram": "eyes", "pa\u015by\u0101mi": "I see", "tv\u0101m": "You", "d\u012bpta": "blazing", "hut\u0101\u015ba-vaktram": "fire coming out of Your mouth", "sva-tejas\u0101": "by Your radiance", "vi\u015bvam": "universe", "idam": "this", "tapantam": "heating."}, "literary_trans": "You are without origin, middle or end. Your glory is unlimited. You have numberless arms, and the sun and moon are Your eyes. I see You with blazing fire coming forth from Your mouth, burning this entire universe by Your own radiance.You are without origin, middle or end. Your glory is unlimited. You have numberless arms, and the sun and moon are Your eyes. I see You with blazing fire coming forth from Your mouth, burning this entire universe by Your own radiance.PurportThere is no limit to the extent of the six opulences of the Supreme Personality of Godhead. Here and in many other places there is repetition, but according to the scriptures, repetition of the glories of K\u1e5b\u1e63\u1e47a is not a literary weakness. It is said that at a time of bewilderment or wonder or of great ecstasy, statements are repeated over and over. That is not a flaw."}